statsfig/__init__.py
statsfig/bernoulli.py
statsfig/binomial.py
statsfig/boxplot.py
statsfig/chisquare.py
statsfig/exponential.py
statsfig/gamma.py
statsfig/normal.py
statsfig/poisson.py
statsfig/uniform.py
statsfig-0.2.4.dist-info/LICENSE
statsfig-0.2.4.dist-info/METADATA
statsfig-0.2.4.dist-info/WHEEL
statsfig-0.2.4.dist-info/top_level.txt
statsfig-0.2.4.dist-info/RECORD
