Metadata-Version: 2.1
Name: statsfig
Version: 0.2.4
Summary: Stats Figures package
Home-page: https://github.com/shinokada/statsfig
Author: Shinichi Okada
Author-email: okada.shin@gmail.com
License: UNKNOWN
Platform: UNKNOWN
Classifier: Programming Language :: Python :: 3
Classifier: License :: OSI Approved :: MIT License
Classifier: Operating System :: OS Independent
Requires-Python: >=3.6
Requires-Dist: matplotlib
Requires-Dist: numpy
Requires-Dist: scipy
Requires-Dist: seaborn
